largeproductaffinity/__init__.py
largeproductaffinity/largeproductaffinity.py
largeproductaffinity-1.1.0.dist-info/LICENSE
largeproductaffinity-1.1.0.dist-info/METADATA
largeproductaffinity-1.1.0.dist-info/WHEEL
largeproductaffinity-1.1.0.dist-info/top_level.txt
largeproductaffinity-1.1.0.dist-info/RECORD
