Metadata-Version: 2.1
Name: largeproductaffinity
Version: 1.1.0
Summary: Description: large_product_affinity is used to obtain Product Affinity using big data without PySpark environment
Author: sarath babu
Author-email: babusarath05@gmail.com
Keywords: python,apriori,product affinity,market basket analysis
Classifier: Development Status :: 1 - Planning
Classifier: Intended Audience :: Developers
Classifier: Programming Language :: Python :: 3
Classifier: Operating System :: Unix
Classifier: Operating System :: MacOS :: MacOS X
Classifier: Operating System :: Microsoft :: Windows
License-File: LICENSE
